LICENSE
MANIFEST.in
README.rst
setup.py
django_world_regions.egg-info/PKG-INFO
django_world_regions.egg-info/SOURCES.txt
django_world_regions.egg-info/dependency_links.txt
django_world_regions.egg-info/requires.txt
django_world_regions.egg-info/top_level.txt
docs/_build/README.html
world_regions/__init__.py
world_regions/admin.py
world_regions/models.py
world_regions/tests.py
world_regions/fixtures/initial_data.json
world_regions/migrations/0001_initial.py
world_regions/migrations/0001_initial.pyc
world_regions/migrations/__init__.py
world_regions/migrations/__init__.pyc