Metadata-Version: 1.1
Name: django-world-regions
Version: 0.1.1
Summary: Simple Django app to group countries in world's regions like *Northern America*, *Eastern Europe*, etc.
Home-page: https://github.com/cesarcruz/django-world-regions
Author: Julio Cesar Rodriguez
Author-email: juliocesarrodriguezcruz@gmail.com
License: MIT License
Platform: UNKNOWN
Classifier: Development Status :: 5 - Production/Stable
Classifier: Environment :: Web Environment
Classifier: Framework :: Django
Classifier: Intended Audience :: Developers
Classifier: License :: OSI Approved :: MIT License
Classifier: Operating System :: OS Independent
Classifier: Programming Language :: Python
Classifier: Programming Language :: Python :: 2.7
